LICENSE
MANIFEST.in
README.md
setup.cfg
setup.py
athiru_cloud_governance.egg-info/PKG-INFO
athiru_cloud_governance.egg-info/SOURCES.txt
athiru_cloud_governance.egg-info/dependency_links.txt
athiru_cloud_governance.egg-info/not-zip-safe
athiru_cloud_governance.egg-info/requires.txt
athiru_cloud_governance.egg-info/top_level.txt
cloud_governance/__init__.py
cloud_governance/cloud_resource_orchestration/__init__.py
cloud_governance/cloud_resource_orchestration/aws/__init__.py
cloud_governance/cloud_resource_orchestration/aws/long_run/__init__.py
cloud_governance/cloud_resource_orchestration/aws/long_run/ec2_long_run.py
cloud_governance/cloud_resource_orchestration/aws/long_run/monitor_in_progress_issues.py
cloud_governance/cloud_resource_orchestration/aws/long_run/monitor_long_run.py
cloud_governance/cloud_resource_orchestration/aws/long_run/tag_long_run.py
cloud_governance/cloud_resource_orchestration/aws/short_run/__init__.py
cloud_governance/cloud_resource_orchestration/aws/short_run/ec2_short_run.py
cloud_governance/cloud_resource_orchestration/common/__init__.py
cloud_governance/cloud_resource_orchestration/common/ec2_monitor_operations.py
cloud_governance/cloud_resource_orchestration/monitor/__init__.py
cloud_governance/cloud_resource_orchestration/monitor/cloud_monitor.py
cloud_governance/common/__init__.py
cloud_governance/common/clouds/__init__.py
cloud_governance/common/clouds/aws/__init__.py
cloud_governance/common/clouds/aws/cloudtrail/__init__.py
cloud_governance/common/clouds/aws/cloudtrail/cloudtrail_operations.py
cloud_governance/common/clouds/aws/cloudwatch/__init__.py
cloud_governance/common/clouds/aws/cloudwatch/cloudwatch_operations.py
cloud_governance/common/clouds/aws/cost_explorer/__init__.py
cloud_governance/common/clouds/aws/cost_explorer/cost_explorer_operations.py
cloud_governance/common/clouds/aws/dynamodb/__init__.py
cloud_governance/common/clouds/aws/dynamodb/dynamodb_operations.py
cloud_governance/common/clouds/aws/ec2/__init__.py
cloud_governance/common/clouds/aws/ec2/ec2_operations.py
cloud_governance/common/clouds/aws/iam/__init__.py
cloud_governance/common/clouds/aws/iam/iam_operations.py
cloud_governance/common/clouds/aws/price/__init__.py
cloud_governance/common/clouds/aws/price/price.py
