Metadata-Version: 2.1
Name: athiru-cloud-governance
Version: 1.1.76
Summary: Cloud Governance Tool
Home-page: https://github.com/redhat-performance/cloud-governance
Author: Red Hat
Author-email: ebattat@redhat.com, athiruma@redhat.com
License: Apache License 2.0
Platform: UNKNOWN
Classifier: License :: OSI Approved :: Apache Software License
Classifier: Programming Language :: Python :: 3
Classifier: Programming Language :: Python :: 3.6
Classifier: Programming Language :: Python :: 3.7
Classifier: Programming Language :: Python :: 3.8
Classifier: Programming Language :: Python :: 3.9
Classifier: Programming Language :: Python :: 3.10
License-File: LICENSE
